{
    "maths1": {
        "name": "Mathematics 1",
        "data": {
            "Assignments": [
                {
                    "title": "",
                    "desc": "",
                    "link": ""
                }
            ],
            "Notes" : [],
            "PYPs" : [],
            "Books" : [
                {
                    "title" : "BV Raman",
                    "desc" : "Mathematics book PDF of BV Raman",
                    "link" : "https://raw.githubusercontent.com/iamwsumit/manit/refs/heads/main/web/content/m1/BV_Ramana.pdf"
                }
            ]
        }
    }
}